.gitignore
CHANGES.txt
CONTRIBUTORS.txt
MANIFEST.in
README.txt
bootstrap.py
buildout.cfg
setup.py
docs/LICENSE.GPL
docs/LICENSE.txt
src/collective/__init__.py
src/collective.mailbox.egg-info/PKG-INFO
src/collective.mailbox.egg-info/SOURCES.txt
src/collective.mailbox.egg-info/dependency_links.txt
src/collective.mailbox.egg-info/entry_points.txt
src/collective.mailbox.egg-info/namespace_packages.txt
src/collective.mailbox.egg-info/not-zip-safe
src/collective.mailbox.egg-info/requires.txt
src/collective.mailbox.egg-info/top_level.txt
src/collective/mailbox/__init__.py
src/collective/mailbox/configure.zcml
src/collective/mailbox/mailboxview.pt
src/collective/mailbox/mailboxview.py
src/collective/mailbox/mailhost.py
src/collective/mailbox/testing.py
src/collective/mailbox/profiles/default/actions.xml
src/collective/mailbox/profiles/default/componentregistry.xml
src/collective/mailbox/profiles/default/metadata.xml
src/collective/mailbox/profiles/default/toolset.xml
src/collective/mailbox/tests/__init__.py
src/collective/mailbox/tests/test_mailhost.py