Metadata-Version: 1.1
Name: collective.mailbox
Version: 1.1.2
Summary: A MailHost that stores outgoing mail.
Home-page: https://github.com/collective/collective.mailbox
Author: Lennart Regebro
Author-email: regebro@gmail.com
License: CC-0
Keywords: mail plone
Platform: UNKNOWN
Classifier: Programming Language :: Python
Classifier: Programming Language :: Python :: 2.7
Classifier: Framework :: Plone :: 4.2
